{
  "name": "List",
  "category": "layout",
  "slug": "components/layout/list",
  "summary": "List component",
  "props": [
    {
      "name": "data",
      "type": "T[]",
      "required": true,
      "description": "Items to render."
    },
    {
      "name": "getTitle",
      "type": "(item: T) => ReactNode",
      "required": true,
      "description": "Primary content for each row."
    },
    {
      "name": "getSubtitle",
      "type": "(item: T) => ReactNode",
      "required": true,
      "description": "Optional secondary line for each row."
    },
    {
      "name": "striped",
      "type": "boolean",
      "required": true,
      "description": "Apply zebra striping."
    },
    {
      "name": "hoverable",
      "type": "boolean",
      "required": true,
      "description": "Hover tint. Enabled by default for non‑striped lists."
    },
    {
      "name": "onReorder",
      "type": "(items: T[]) => void",
      "required": true,
      "description": "Fires after a drag operation ends with the new order."
    },
    {
      "name": "reorderable",
      "type": "boolean",
      "required": true,
      "description": "Enable drag‑and‑drop reordering. When false, drag is disabled."
    },
    {
      "name": "selectable",
      "type": "boolean",
      "required": true,
      "description": "Enable single selection. Click or drag to select the active item."
    },
    {
      "name": "selected",
      "type": "T | null",
      "required": true,
      "description": "Controlled selected item (by reference)."
    },
    {
      "name": "defaultSelected",
      "type": "T | null",
      "required": true,
      "description": "Uncontrolled initial selected item."
    },
    {
      "name": "onSelectionChange",
      "type": "(item: T, index: number) => void",
      "required": true,
      "description": "Fires on selection change (click or drag‑select)."
    },
    {
      "name": "sx",
      "type": "Sx",
      "required": true
    },
    {
      "name": "preset",
      "type": "string | string[]",
      "required": false,
      "description": "Apply style presets."
    },
    {
      "name": "HTML ul props",
      "type": "Omit<React.HTMLAttributes<HTMLUListElement>, 'children'>",
      "required": false,
      "description": "Standard HTML attributes for <ul> (excluding &apos;children&apos;) pass through."
    }
  ],
  "cssVars": [],
  "bestPractices": [],
  "examples": [],
  "docsUrl": "/components/layout/ListDemoPage",
  "sourceFiles": [
    "src/components/layout/List.tsx",
    "docs/src/pages/components/layout/ListDemoPage.tsx"
  ],
  "version": "0.30.1"
}